tom_scimma/__init__.py
tom_scimma/scimma.py
tom_scimma/templates/tom_scimma/partials/submit_upstream_scimma_form.html
tom_scimma/templatetags/scimma_extras.py
tom_scimma/tests/__init__.py
tom_scimma/tests/boot_django.py
tom_scimma/tests/django_shell.py
tom_scimma/tests/run_canary_tests.py
tom_scimma/tests/run_tests.py
tom_scimma/tests/tests.py
tom_scimma/tests/tests_canary.py
tom_scimma/tests/utils.py
tom_scimma-1.1.6.dist-info/LICENSE
tom_scimma-1.1.6.dist-info/METADATA
tom_scimma-1.1.6.dist-info/WHEEL
tom_scimma-1.1.6.dist-info/top_level.txt
tom_scimma-1.1.6.dist-info/RECORD
