Metadata-Version: 2.1
Name: tom-scimma
Version: 1.1.6
Summary: Skip/Hopskotch broker module for the TOM Toolkit
Home-page: https://scimma.org
Author: TOM Toolkit Project
Author-email: dcollom@lco.global
License: UNKNOWN
Keywords: tomtoolkit,astronomy,astrophysics,cosmology,science,fits,observatory,scimma
Platform: UNKNOWN
Classifier: Development Status :: 3 - Alpha
Classifier: Intended Audience :: Science/Research
Classifier: License :: OSI Approved :: BSD License
Classifier: Operating System :: OS Independent
Classifier: Programming Language :: Python :: 3
Classifier: Programming Language :: Python :: 3.7
Classifier: Topic :: Scientific/Engineering :: Astronomy
Classifier: Topic :: Scientific/Engineering :: Physics
License-File: LICENSE
Requires-Dist: tomtoolkit (~=2.10)
Requires-Dist: hop-client (~=0.5)
Provides-Extra: test
Requires-Dist: factory-boy (~=3.1) ; extra == 'test'
